CAImport/APITools.py
CAImport/__init__.py
CAImport/tools.py
CAImport-1.0.9.dist-info/LICENSE
CAImport-1.0.9.dist-info/METADATA
CAImport-1.0.9.dist-info/WHEEL
CAImport-1.0.9.dist-info/top_level.txt
CAImport-1.0.9.dist-info/RECORD
